Workbook

Sheet Main Model
C1: Sahil Rajendra Kamble
A2: VARUN BEVERAGES
A3: Assumptions
B5: First year of forecast | D5: 2026 | K5: =$D$5 -> 2026 | L5: =K5+1 -> 2027 | M5: =L5+1 -> 2028 | N5: =M5+1 -> 2029 | O5: =N5+1 -> 2030
C6: Inflation Rate for Capex | D6: 0.05
B8: Scenarios & Sensitivity Analysis
B10: India Volume Growth % | D10: 1 | K10: =CHOOSE($D$10,K12,K13,K14) -> 0.11 | L10: =CHOOSE($D$10,L12,L13,L14) -> 0.1 | M10: =CHOOSE($D$10,M12,M13,M14) -> 0.1 | N10: =CHOOSE($D$10,N12,N13,N14) -> 0.1 | O10: =CHOOSE($D$10,O12,O13,O14) -> 0.1
B12: Base Case | K12: 0.11 | L12: 0.1 | M12: 0.1 | N12: 0.1 | O12: 0.1
B13: Best Case | K13: 0.14 | L13: 0.13 | M13: 0.13 | N13: 0.13 | O13: 0.13
B14: Worst Case | K14: 0.08 | L14: 0.08 | M14: 0.07 | N14: 0.07 | O14: 0.07
B16: International Volume Growth % | D16: 1 | K16: =CHOOSE($D$16,K18,K19,K20) -> 0.3 | L16: =CHOOSE($D$16,L18,L19,L20) -> 0.15 | M16: =CHOOSE($D$16,M18,M19,M20) -> 0.15 | N16: =CHOOSE($D$16,N18,N19,N20) -> 0.15 | O16: =CHOOSE($D$16,O18,O19,O20) -> 0.15
B18: Base Case | K18: 0.3 | L18: 0.15 | M18: 0.15 | N18: 0.15 | O18: 0.15
B19: Best Case | K19: 0.35 | L19: 0.2 | M19: 0.2 | N19: 0.2 | O19: 0.2
B20: Worst Case | K20: 0.25 | L20: 0.1 | M20: 0.1 | N20: 0.1 | O20: 0.1
B22: India realization per case Growth % | D22: 1 | K22: =CHOOSE($D$22,K24,K25,K26) -> 0.005 | L22: =CHOOSE($D$22,L24,L25,L26) -> 0.015 | M22: =CHOOSE($D$22,M24,M25,M26) -> 0.02 | N22: =CHOOSE($D$22,N24,N25,N26) -> 0.025 | O22: =CHOOSE($D$22,O24,O25,O26) -> 0.025
B24: Base Case | K24: 0.005 | L24: 0.015 | M24: 0.02 | N24: 0.025 | O24: 0.025
B25: Best Case | K25: 0.02 | L25: 0.03 | M25: 0.04 | N25: 0.04 | O25: 0.04
B26: Worst Case | K26: -0.015 | L26: -0.005 | M26: 0.005 | N26: 0.01 | O26: 0.01
B28: International realization per case Growth % | D28: 1 | K28: =CHOOSE($D$28,K30,K31,K32) -> 0.06 | L28: =CHOOSE($D$28,L30,L31,L32) -> 0.025 | M28: =CHOOSE($D$28,M30,M31,M32) -> 0.025 | N28: =CHOOSE($D$28,N30,N31,N32) -> 0.025 | O28: =CHOOSE($D$28,O30,O31,O32) -> 0.025
B30: Base Case | K30: 0.06 | L30: 0.025 | M30: 0.025 | N30: 0.025 | O30: 0.025
B31: Best Case | K31: 0.09 | L31: 0.045 | M31: 0.04 | N31: 0.04 | O31: 0.04
B32: Worst Case | K32: 0.01 | L32: 0 | M32: 0.01 | N32: 0.015 | O32: 0.015
B35: India Revenue
C36: Volume growth % | D36: (%) | K36: =K10 -> 0.11 | L36: =L10 -> 0.1 | M36: =M10 -> 0.1 | N36: =N10 -> 0.1 | O36: =O10 -> 0.1
C37: Realization per case growth % | D37: (%) | K37: =K22 -> 0.005 | L37: =L22 -> 0.015 | M37: =M22 -> 0.02 | N37: =N22 -> 0.025 | O37: =O22 -> 0.025
B39: International Revenue
C40: Volume growth rate | D40: (%) | K40: =K16 -> 0.3 | L40: =L16 -> 0.15 | M40: =M16 -> 0.15 | N40: =N16 -> 0.15 | O40: =O16 -> 0.15
C41: Realization per case growth % | D41: (%) | K41: =K28 -> 0.06 | L41: =L28 -> 0.025 | M41: =M28 -> 0.025 | N41: =N28 -> 0.025 | O41: =O28 -> 0.025
C42: Excise Duty % | D42: (%) | K42: =$J$246 -> 0.077229313 | L42: =$J$246 -> 0.077229313 | M42: =$J$246 -> 0.077229313 | N42: =$J$246 -> 0.077229313 | O42: =$J$246 -> 0.077229313
B45: Cost Schedule
C46: Margin for Cost of materials consumed | D46: (%) | K46: =$J$258 -> 0.44400923 | L46: =$J$258 -> 0.44400923 | M46: =$J$258 -> 0.44400923 | N46: =$J$258 -> 0.44400923 | O46: =$J$258 -> 0.44400923
C47: Other Expenses | D47: (%) | K47: =$J$263 -> 0.22556761 | L47: =$J$263 -> 0.22556761 | M47: =$J$263 -> 0.22556761 | N47: =$J$263 -> 0.22556761 | O47: =$J$263 -> 0.22556761
B50: Capex-Split Trend
C52: Land | E52: 0.02042
C53: Building + Plant & Equipment | E53: 0.81134
C54: Distribution & Others | E54: 0.16824
B56: Fixed Asset Schedule
C57: India Expansion Capex | K57: 5000 | L57: =K57*(1+$D$6) -> 5250 | M57: =L57*(1+$D$6) -> 5512.5 | N57: =M57*(1+$D$6) -> 5788.125 | O57: =N57*(1+$D$6) -> 6077.5312
C58: Total Maintenance Capex | J58: 10634.17 | K58: =J58*(1+$D$6) -> 11165.879 | L58: =K406 -> 13102.579 | M58: =L406 -> 14023.968 | N58: =M406 -> 15004.45 | O58: =N406 -> 16083.35
C59: Expansion Towards South Africa and CSD line in Kenya (CWIP) | K59: 4900
C60: CWIP Transfer to PPE
C61: Inorganic implied PPE added due to acquisition of Twizza South Africa | K61: 3144
C62: Total Capex | K62: =SUM(K57:K61) -> 24209.878 | L62: =SUM(L57:L61) -> 18352.579 | M62: =SUM(M57:M61) -> 19536.468 | N62: =SUM(N57:N61) -> 20792.575 | O62: =SUM(O57:O61) -> 22160.881
C64: CWIP routing share to transfer to Building, Plant & Equipment (50%) | J64: 0.5
B67: Debt Schedule
C68: Minimum Cash Balance | J68: 1889.34 | K68: =J68*(1+K283) -> 2270.6546 | L68: =K68*(1+L283) -> 2588.4621 | M68: =L68*(1+M283) -> 2961.5053 | N68: =M68*(1+N283) -> 3400.0412 | O68: =N68*(1+O283) -> 3905.3843
C69: ST Interest rate | K69: 0.1025 | L69: =K69 -> 0.1025 | M69: =L69 -> 0.1025 | N69: =M69 -> 0.1025 | O69: =N69 -> 0.1025
C70: Interest rate on Cash and cash equivalents | K70: 0.06 | L70: =K70 -> 0.06 | M70: =L70 -> 0.06 | N70: =M70 -> 0.06 | O70: =N70 -> 0.06
B72: TWIZZA Integaration
C73: Goodwill | K73: 4689.19
C74: Other Intangible Assets | K74: 3481.33
C75: PPE Implied | K75: 3144
C76: Total | K76: =SUM(K73:K75) -> 11314.52
A80: Income Statement
A82: Income Statement (in millions of INR) | F82: =G82-1 -> 2021 | G82: =H82-1 -> 2022 | H82: =I82-1 -> 2023 | I82: =J82-1 -> 2024 | J82: =K82-1 -> 2025 | K82: =K5 -> 2026 | L82: =L5 -> 2027 | M82: =M5 -> 2028 | N82: =N5 -> 2029 | O82: =O5 -> 2030
B84: 1. Income
C85: Revenue from operations | F85: 89582.91 | G85: 133905.58 | H85: 163210.63 | I85: 204813.28 | J85: 222255.84 | K85: =K87-K86 -> 268206.5 | L85: =L87-L86 -> 306039.71 | M85: =M87-M86 -> 350455.15 | N85: =N87-N86 -> 402673.4 | O85: =O87-O86 -> 462896.41
C86: Excise Duty | F86: -1350.61 | G86: -2174.16 | H86: -2784.82 | I86: -4736.78 | J86: -5402.05 | K86: =-K244 -> -7586.3524 | L86: =-L244 -> -8942.4129 | M86: =-M244 -> -10540.869 | N86: =-N244 -> -12425.05 | O86: =-O244 -> -14646.027
B87: Net Revenues | F87: =F85+F86 -> 88232.3 | G87: =G85+G86 -> 131731.42 | H87: =H85+H86 -> 160425.81 | I87: =I85+I86 -> 200076.5 | J87: =J85+J86 -> 216853.79 | K87: =K242 -> 260620.14 | L87: =L242 -> 297097.3 | M87: =M242 -> 339914.28 | N87: =N242 -> 390248.35 | O87: =O242 -> 448250.38
C88: Other Income | F88: 679.25 | G88: 388.49 | H88: 793.59 | I88: 1212.68 | J88: 3523.48 | K88: =K424 -> 756.83035 | L88: =L424 -> 918.221 | M88: =M424 -> 2298.3253 | N88: =N424 -> 4044.1812 | O88: =O424 -> 6220.2528
B90: 2. Expenses
C91: Cost of materials consumed | F91: 39689.13 | G91: 64170.92 | H91: 70264.61 | I91: 82937.43 | J91: 93370.62 | K91: =K87*K46 -> 115717.75 | L91: =L87*L46 -> 131913.94 | M91: =M87*M46 -> 150925.08 | N91: =N87*N46 -> 173273.87 | O91: =O87*O46 -> 199027.31
C92: Purchase of stock-in-trade | F92: 1654.69 | G92: 1885.71 | H92: 4626.96 | I92: 6859.21 | J92: 3694.53 | K92: =K274 -> 5902.0163 | L92: =L274 -> 6728.0798 | M92: =M274 -> 7697.7151 | N92: =N274 -> 8837.583 | O92: =O274 -> 10151.1
C93: Changes in inventories of FG, WIP and stock-in-trade | F93: -997.22 | G93: -3445.07 | H93: -842.69 | I93: -749.4 | J93: 89.14 | K93: 0 | L93: 0 | M93: 0 | N93: 0 | O93: 0
C94: Employee benefits expense | F94: 10076.99 | G94: 12166.42 | H94: 14465.87 | I94: 18850.26 | J94: 22007.43 | K94: =K269 -> 25667.936 | L94: =L269 -> 29260.496 | M94: =M269 -> 33477.451 | N94: =N269 -> 38434.75 | O94: =O269 -> 44147.249
C95: Finance costs | F95: 1847 | G95: 1861.22 | H95: 2680.99 | I95: 4503.86 | J95: 1695.79 | K95: =K451 -> 1538.5461 | L95: =L451 -> 760.40856 | M95: =M451 -> 654.47932 | N95: =N451 -> 571.32916 | O95: =O451 -> 530.73154
C96: Depreciation, amortization expense | F96: 5312.62 | G96: 6171.89 | H96: 6809.06 | I96: 9473.86 | J96: 12164.63 | K96: =K495 -> 14704.663 | L96: =L495 -> 15918.178 | M96: =M495 -> 16898.66 | N96: =N495 -> 17977.56 | O96: =O495 -> 19148.93
C97: Other expenses | F97: 21262.26 | G97: 29072.39 | H97: 35816.21 | I97: 45068.29 | J97: 47198.38 | K97: =K264 -> 58787.462 | L97: =L264 -> 67015.527 | M97: =M264 -> 76673.65 | N97: =N264 -> 88027.387 | O97: =O264 -> 101110.77
B98: Total Expenses | F98: =SUM(F91:F97) -> 78845.47 | G98: =SUM(G91:G97) -> 111883.48 | H98: =SUM(H91:H97) -> 133821.01 | I98: =SUM(I91:I97) -> 166943.51 | J98: =SUM(J91:J97) -> 180220.52 | K98: =SUM(K91:K97) -> 222318.37 | L98: =SUM(L91:L97) -> 251596.63 | M98: =SUM(M91:M97) -> 286327.03 | ... O98: =SUM(O91:O97) -> 374116.08
B100: EBITDA | F100: =F87-F98+F96+F95 -> 16546.45 | G100: =G87-G98+G96+G95 -> 27881.05 | H100: =H87-H98+H96+H95 -> 36094.85 | I100: =I87-I98+I96+I95 -> 47110.71 | J100: =J87-J98+J96+J95 -> 50493.69 | K100: =K87-K98+K96+K95 -> 54544.979 | L100: =L87-L98+L96+L95 -> 62179.254 | M100: =M87-M98+M96+M95 -> 71140.385 | ... O100: =O87-O98+O96+O95 -> 93813.961
B102: 3. Profit before share of loss of associate and joint venture | F102: =F87+F88-F98 -> 10066.08 | G102: =G87+G88-G98 -> 20236.43 | H102: =H87+H88-H98 -> 27398.39 | I102: =I87+I88-I98 -> 34345.67 | J102: =J87+J88-J98 -> 40156.75 | K102: =K87+K88-K98 -> 39058.601 | L102: =L87+L88-L98 -> 46418.889 | M102: =M87+M88-M98 -> 55885.57 | ... O102: =O87+O88-O98 -> 80354.552
B103: 4. Share of loss of associate and joint venture | F103: 0 | G103: -0.06 | H103: -4.79 | I103: -14.78 | J103: -60.27 | K103: 0 | L103: 0 | M103: 0 | N103: 0 | O103: 0
B104: 5. Profit before tax | F104: =F102+F103 -> 10066.08 | G104: =G102+G103 -> 20236.37 | H104: =H102+H103 -> 27393.6 | I104: =I102+I103 -> 34330.89 | J104: =J102+J103 -> 40096.48 | K104: =K102+K103 -> 39058.601 | L104: =L102+L103 -> 46418.889 | M104: =M102+M103 -> 55885.57 | ... O104: =O102+O103 -> 80354.552
B105: 6. Tax expense | F105: -2605.56 | G105: -4735.23 | H105: -6375.47 | I105: -7988.04 | J105: -9476.06 | K105: =-K519 -> -9136.3943 | L105: =-L519 -> -10858.076 | M105: =-M519 -> -13072.476 | N105: =-N519 -> -15712.086 | O105: =-O519 -> -18796.139
B106: 7. Net Income | F106: =F104+F105 -> 7460.52 | G106: =G104+G105 -> 15501.14 | H106: =H104+H105 -> 21018.13 | I106: =I104+I105 -> 26342.85 | J106: =J104+J105 -> 30620.42 | K106: =K104+K105 -> 29922.206 | L106: =L104+L105 -> 35560.812 | M106: =M104+M105 -> 42813.095 | ... O106: =O104+O105 -> 61558.414
B107: 8. Non-controlling interest | F107: -520 | G107: -553.81 | H107: -458.91 | I107: -396.52 | J107: -255.53
B108: 9. Net income attributable to equity shareholders | F108: =F106+F107 -> 6940.52 | G108: =G106+G107 -> 14947.33 | H108: =H106+H107 -> 20559.22 | I108: =I106+I107 -> 25946.33 | J108: =J106+J107 -> 30364.89 | K108: =K106+K107 -> 29922.206 | L108: =L106+L107 -> 35560.812 | M108: =M106+M107 -> 42813.095 | ... O108: =O106+O107 -> 61558.414
B111: Weighted-average share count (basic) | D111: (000s) | F111: 3246825 | G111: 3246825 | H111: 3246875 | I111: 3278350 | J111: 3381750 | K111: =K540 -> 3381750 | L111: =L540 -> 3381750 | M111: =M540 -> 3381750 | N111: =N540 -> 3381750 | O111: =O540 -> 3381750
B112: Weighted-average share count (diluted) | D112: (000s) | F112: 3248500 | G112: 3248750 | H112: 3248928 | I112: 3280500 | J112: 3383500 | K112: =K543 -> 3383500 | L112: =L543 -> 3383500 | M112: =M543 -> 3383500 | N112: =N543 -> 3383500 | O112: =O543 -> 3383500
B113: EPS
B114: Basic | D114: INR | F114: =(F$108/F111)*1000 -> 2.1376329 | G114: =(G$108/G111)*1000 -> 4.6036759 | H114: =(H$108/H111)*1000 -> 6.3320023 | I114: =(I$108/I111)*1000 -> 7.9144478 | J114: =(J$108/J111)*1000 -> 8.9790464 | K114: =(K$108/K111)*1000 -> 8.8481426 | L114: =(L$108/L111)*1000 -> 10.515506 | M114: =(M$108/M111)*1000 -> 12.660041 | ... O114: =(O$108/O111)*1000 -> 18.203124
B115: Diluted | D115: INR | F115: =(F$108/F112)*1000 -> 2.1365307 | G115: =(G$108/G112)*1000 -> 4.6009481 | H115: =(H$108/H112)*1000 -> 6.3280011 | I115: =(I$108/I112)*1000 -> 7.9092608 | J115: =(J$108/J112)*1000 -> 8.9744022 | K115: =(K$108/K112)*1000 -> 8.8435662 | L115: =(L$108/L112)*1000 -> 10.510067 | M115: =(M$108/M112)*1000 -> 12.653493 | ... O115: =(O$108/O112)*1000 -> 18.193709
A119: Cash Flow Statement
A121: Cash Flow Statement (in millions of INR) | F121: =G121-1 -> 2021 | G121: =H121-1 -> 2022 | H121: =I121-1 -> 2023 | I121: =J121-1 -> 2024 | J121: =K121-1 -> 2025 | K121: =K$82 -> 2026 | L121: =L$82 -> 2027 | M121: =M$82 -> 2028 | N121: =N$82 -> 2029 | O121: =O$82 -> 2030
B122: A. Cash Flows from Operating activities
C123: Profit before tax and share of loss in associates and joint ventures | F123: 10066.08 | G123: 20236.43 | H123: 27398.39 | I123: 34345.67 | J123: 40156.75 | K123: =K102 -> 39058.601 | L123: =L102 -> 46418.889 | M123: =M102 -> 55885.57 | N123: =N102 -> 67170.055 | O123: =O102 -> 80354.552
B125: Adjustment to reconcile profit before tax to net cash flows:
C126: Depreciation and impairment on property, plant and equipment | F126: 5037.54 | G126: 5830.99 | H126: 6409.04 | I126: 8386.95 | J126: 10634.17 | K126: =K406 -> 13102.579 | L126: =L406 -> 14023.968 | M126: =M406 -> 15004.45 | N126: =N406 -> 16083.35 | O126: =O406 -> 17254.719
C127: Amortisation of intangible assets and right of use assets | F127: 275.08 | G127: 340.9 | H127: 400.02 | I127: 1086.91 | J127: 1530.46 | K127: =K494 -> 1602.0835 | L127: =L494 -> 1894.2103 | M127: =M494 -> 1894.2103 | N127: =N494 -> 1894.2103 | O127: =O494 -> 1894.2103
C128: Interest expense at amortised cost | F128: 1850.37 | G128: 1854.49 | H128: 2680.99 | I128: 4503.86 | J128: 1695.79 | K128: =K451 -> 1538.5461 | L128: =L451 -> 760.40856 | M128: =M451 -> 654.47932 | N128: =N451 -> 571.32916 | O128: =O451 -> 530.73154
C129: Interest income at amortised cost | F129: -145.16 | G129: -228.29 | H129: -238 | I129: -419 | J129: -317.65 | K129: =-K424 -> -756.83035 | L129: =-L424 -> -918.221 | M129: =-M424 -> -2298.3253 | N129: =-N424 -> -4044.1812 | O129: =-O424 -> -6220.2528
C130: Total Provisions & Non-Cash Write-offs | F130: 0.54 | G130: 90.02 | H130: -249.65 | I130: -532.57 | J130: 69.62 | K130: 0 | L130: 0 | M130: 0 | N130: 0 | O130: 0
C131: Gains / Losses on Asset Disposals & Investments | F131: 258.01 | G131: 619.59 | H131: 839.32 | I131: 739.41 | J131: -838.84 | K131: 0 | L131: 0 | M131: 0 | N131: 0 | O131: 0
C132: Other Non-Operating Accounting Adjustments | F132: -1098.5 | G132: -1258.62 | H132: 81.87 | I132: -330.72 | J132: -3245.11 | K132: =K502 -> 976.45801 | L132: =L502 -> 813.83097 | M132: =M502 -> 955.27673 | N132: =N502 -> 1122.9885 | O132: =O502 -> 1294.0659
C134: Operating profit before working capital changes | F134: =F123+(SUM(F126:F132)) -> 16243.96 | G134: =G123+(SUM(G126:G132)) -> 27485.51 | H134: =H123+(SUM(H126:H132)) -> 37321.98 | I134: =I123+(SUM(I126:I132)) -> 47780.51 | J134: =J123+(SUM(J126:J132)) -> 49685.19 | K134: =K123+(SUM(K126:K132)) -> 55521.437 | L134: =L123+(SUM(L126:L132)) -> 62993.085 | M134: =M123+(SUM(M126:M132)) -> 72095.661 | ... O134: =O123+(SUM(O126:O132)) -> 95108.027
B136: Working capital adjustments
C137: Inventories | F137: -5192.83 | G137: -5568.33 | H137: -1601.73 | I137: -4787.7 | J137: 147.84 | K137: =K309 -> -7064.7502 | L137: =L309 -> -5120.2135 | M137: =M309 -> -6010.1188 | N137: =N309 -> -7065.2767 | O137: =O309 -> -8141.6092
C138: Trade Receivables | F138: 146.56 | G138: -1233.8 | H138: -730.18 | I138: -1332.15 | J138: -2851.03 | K138: =K308 -> -2520.8474 | L138: =L308 -> -2101.0056 | M138: =M308 -> -2466.1654 | N138: =N308 -> -2899.1341 | O138: =O308 -> -3340.7916
C139: Inc. in Financial & Other Assets | F139: -921.85 | G139: -3257.13 | H139: -4572.18 | I139: -5224.3 | J139: 2230.71 | K139: =K310 -> -3411.0155 | L139: =L310 -> -2842.918 | M139: =M310 -> -3337.0239 | N139: =N310 -> -3922.8837 | O139: =O310 -> -4520.5005
C140: Inc. in Financial & Other Liabilities & Provisions | F140: 3280.66 | G140: 4207.33 | H140: 169.28 | I140: 4650.27 | J140: -5238.06 | K140: =K306 -> 4738.3684 | L140: =L306 -> 3320.1724 | M140: =M306 -> 3897.2263 | N140: =N306 -> 4581.4372 | O140: =O306 -> 5279.3787
...

Sheet Term Loans
A3: Indian rupee loan from banks
B5: Term loan - 1
C7: Year | D7: Opening Balance | E7: Interest Rate | F7: Interest Payment | G7: Principal Repayment | H7: Closing Balance | L7: Period | M7: Days | N7: Balance | O7: Interest = Bal * IR *(days/365)
C8: 2026 | D8: 560.29 | E8: 0.0669 | F8: =SUM(O8:O10) -> 26.198269 | G8: 309.4 | H8: =D8-G8 -> 250.89 | L8: 1-Jan to 31-May26 | M8: 151 | N8: 560.29 | O8: =N8*$E$8*(M8/365) -> 15.506832
C9: 2027 | D9: =H8 -> 250.89 | E9: 0.0669 | F9: =SUM(O11:O12) -> 7.6335173 | G9: =250.89 -> 250.89 | H9: =D9-G9 -> 0 | L9: 1-June to 30-June26 | M9: 30 | N9: 405.59 | O9: =N9*$E$8*(M9/365) -> 2.2301894
L10: 1-July to 31-Dec26 | M10: 184 | N10: 250.89 | O10: =N10*$E$8*(M10/365) -> 8.4612481
L11: 1-Jan to 31-May27 | M11: 151 | N11: 250.89 | O11: =N11*$E$9*(M11/365) -> 6.9437416
L12: 1-June to 30-June27 | M12: 30 | N12: 125.445 | O12: =N12*$E$9*(M12/365) -> 0.68977566
B14: Term loan - 2
C16: Year | D16: Opening Balance | E16: Interest Rate | F16: Interest Payment | G16: Principal Repayment | H16: Closing Balnce | L16: Period | M16: Days | N16: Balance | O16: Interest = Bal * IR *(days/365)
C17: 2026 | D17: 282.64 | E17: 0.0669 | F17: =SUM(O17:O19) -> 13.754075 | G17: 141.32 | H17: =D17-G17 -> 141.32 | L17: 1-Jan to 31-May26 | M17: 151 | N17: 282.64 | O17: =N17*$E$17*(M17/365) -> 7.8224685
C18: 2027 | D18: =H17 -> 141.32 | E18: 0.0669 | F18: =SUM(O20:O21) -> 4.2997675 | G18: 141.32 | H18: =D18-G18 -> 0 | L18: 1-June to 30-June26 | M18: 30 | N18: 211.98 | O18: =N18*$E$17*(M18/365) -> 1.1655996
L19: 1-July to 31-Dec26 | M19: 184 | N19: 141.32 | O19: =N19*$E$17*(M19/365) -> 4.7660073
L20: 1-Jan to 31-May27 | M20: 151 | N20: 141.32 | O20: =N20*$E$18*(M20/365) -> 3.9112343
L21: 1-June to 30-June27 | M21: 30 | N21: 70.66 | O21: =N21*$E$18*(M21/365) -> 0.38853321
B23: Term loan - 4
C25: Year | D25: Opening Balance | E25: Interest Rate | F25: Interest Payment | G25: Principal Repayment | H25: Closing Balnce | L25: Period | M25: Days | N25: Balance | O25: Interest = Bal * IR *(days/365)
C26: 2026 | D26: 170.5 | E26: 0.0669 | F26: =SUM(O26:O28) -> 9.7257167 | G26: 46.08 | H26: =D26-G26 -> 124.42 | L26: 1-Jan to 31-May26 | M26: 151 | N26: 170.5 | O26: =N26*$E$26*(M26/365) -> 4.7188327
C27: 2027 | D27: =H26 -> 124.42 | E27: 0.0669 | F27: =SUM(O29:O31) -> 5.9703796 | G27: 64.52 | H27: =D27-G27 -> 59.9 | L27: 1-June to 30-June26 | M27: 30 | N27: 147.46 | O27: =N27*$E$26*(M27/365) -> 0.810828
C28: 2028 | D28: =H27 -> 59.9 | E28: 0.0669 | F28: =SUM(O32:O33) -> 1.8098008 | G28: 59.9 | H28: =D28-G28 -> 0 | L28: 1-July to 31-Dec26 | M28: 184 | N28: 124.42 | O28: =N28*$E$26*(M28/365) -> 4.196056
L29: 1-Jan to 31-May27 | M29: 151 | N29: 124.42 | O29: =N29*$E$27*(M29/365) -> 3.4435025
L30: 1-June to 30-June27 | M30: 30 | N30: 92.16 | O30: =N30*$E$27*(M30/365) -> 0.50675375
L31: 1-July to 31-Dec27 | M31: 184 | N31: 59.9 | O31: =N31*$E$27*(M31/365) -> 2.0201234
L32: 1-Jan to 31-May28 | M32: 151 | N32: 59.9 | O32: =N32*$E$28*(M32/365) -> 1.6578187
L33: 1-June to 30-June28 | M33: 30 | N33: 27.64 | O33: =N33*$E$28*(M33/365) -> 0.15198214
B35: Term loan - 5
C37: Year | D37: Opening Balance | E37: Interest Rate | F37: Interest Payment | G37: Principal Repayment | H37: Closing Balance | L37: Period | M37: Days | N37: Balance | O37: Interest = Bal * IR *(days/365)
C38: 2026 | D38: 2400 | E38: 0.0669 | F38: =SUM(O38:O40) -> 138.67545 | G38: 600 | H38: =D38-G38 -> 1800 | L38: 1-Jan to 31-May26 | M38: 151 | N38: 2400 | O38: =N38*$E$38*(M38/365) -> 66.423452
C39: 2027 | D39: =H38 -> 1800 | E39: 0.0669 | F39: =SUM(O41:O43) -> 98.535452 | G39: 600 | H39: =D39-G39 -> 1200 | L39: 1-June to 30-June26 | M39: 30 | N39: 2100 | O39: =N39*$E$38*(M39/365) -> 11.547123
C40: 2028 | D40: =H39 -> 1200 | E40: 0.0669 | F40: =SUM(O44:O46) -> 58.395452 | G40: 600 | H40: =D40-G40 -> 600 | L40: 1-July to 31-Dec26 | M40: 184 | N40: 1800 | O40: =N40*$E$38*(M40/365) -> 60.704877
C41: 2029 | D41: =H40 -> 600 | E41: 0.0669 | F41: =SUM(O47:O48) -> 18.255452 | G41: 600 | H41: =D41-G41 -> 0 | L41: 1-Jan to 31-May27 | M41: 151 | N41: 1800 | O41: =N41*$E$39*(M41/365) -> 49.817589
L42: 1-June to 30-June27 | M42: 30 | N42: 1500 | O42: =N42*$E$39*(M42/365) -> 8.2479452
L43: 1-July to 31-Dec27 | M43: 184 | N43: 1200 | O43: =N43*$E$39*(M43/365) -> 40.469918
L44: 1-Jan to 31-May28 | M44: 151 | N44: 1200 | O44: =N44*$E$40*(M44/365) -> 33.211726
L45: 1-June to 30-June28 | M45: 30 | N45: 900 | O45: =N45*$E$40*(M45/365) -> 4.9487671
L46: 1-July to 31-Dec27 | M46: 184 | N46: 600 | O46: =N46*$E$40*(M46/365) -> 20.234959
L47: 1-Jan to 31-May28 | M47: 151 | N47: 600 | O47: =N47*$E$41*(M47/365) -> 16.605863
L48: 1-June to 30-June28 | M48: 30 | N48: 300 | O48: =N48*$E$41*(M48/365) -> 1.649589
B50: Total
C51: Year | D51: Opening Balance | E51: Interest Paid | F51: Principal Paid | G51: Closing Balance
C52: 2026 | D52: =D8+D17+D26+D38 -> 3413.43 | E52: =F8+F17+F26+F38 -> 188.35351 | F52: =G8+G17+G26+G38 -> 1096.8 | G52: =H8+H17+H26+H38 -> 2316.63
C53: =C52+1 -> 2027 | D53: =D9+D18+D27+D39 -> 2316.63 | E53: =F9+F18+F27+F39 -> 116.43912 | F53: =G9+G18+G27+G39 -> 1056.73 | G53: =H9+H18+H27+H39 -> 1259.9
C54: =C53+1 -> 2028 | D54: =D10+D19+D28+D40 -> 1259.9 | E54: =F10+F19+F28+F40 -> 60.205253 | F54: =G10+G19+G28+G40 -> 659.9 | G54: =H10+H19+H28+H40 -> 600
C55: =C54+1 -> 2029 | D55: =D11+D20+D29+D41 -> 600 | E55: =F11+F20+F29+F41 -> 18.255452 | F55: =G11+G20+G29+G41 -> 600 | G55: =H11+H20+H29+H41 -> 0
C56: =C55+1 -> 2030 | D56: =D12+D21+D30+D42 -> 0 | E56: =F12+F21+F30+F42 -> 0 | F56: =G12+G21+G30+G42 -> 0 | G56: =H12+H21+H30+H42 -> 0
A60: Term Loan at Varun Beverages Morocco
B62: Term Loan - 6
C64: Last Payment in JAN 2026 | D64: 13.16
B66: Term Loan - 7 | D66: 1 DHS = | E66: 8.5985
C68: Year | D68: Opening Balance | E68: Interest Rate | F68: Interest in INR | G68: Principal repayment | H68: Closing Balance | L68: Period | M68: Days | N68: Balance | O68: Interest
C69: 2026 | D69: =N69*E66 -> 247.6368 | E69: 0.0425 | F69: =(SUM(O69:O72))*E66 -> 8.7592566 | G69: =3.2*4*E66 -> 110.0608 | H69: =D69-G69 -> 137.576 | L69: 2026 Q1 | M69: 90 | N69: 28.8 | O69: =N69*$E$69*(M69/365) -> 0.30180822
C70: 2027 | D70: =H69 -> 137.576 | E70: 0.0425 | F70: =(SUM(O73:O76))*E66 -> 4.0816726 | G70: 110.06 | H70: =D70-G70 -> 27.516 | L70: Q2 | M70: 91 | N70: =N69-3.2 -> 25.6 | O70: =N70*$E$69*(M70/365) -> 0.27125479
C71: 2028 | D71: =H70 -> 27.516 | E71: 0.0425 | F71: =O77*E66 -> 0.29154804 | G71: =D71 -> 27.516 | H71: =D71-G71 -> 0 | L71: Q3 | M71: 92 | N71: =N70-3.2 -> 22.4 | O71: =N71*$E$69*(M71/365) -> 0.23995616
L72: Q4 | M72: 92 | N72: =N71-3.2 -> 19.2 | O72: =N72*$E$69*(M72/365) -> 0.20567671
L73: 2027 Q1 | M73: 90 | N73: =N72-3.2 -> 16 | O73: =N73*$E$69*(M73/365) -> 0.16767123
L74: Q2 | M74: 91 | N74: =N73-3.2 -> 12.8 | O74: =N74*$E$69*(M74/365) -> 0.1356274
L75: Q3 | M75: 92 | N75: =N74-3.2 -> 9.6 | O75: =N75*$E$69*(M75/365) -> 0.10283836
L76: Q4 | M76: 92 | N76: =N75-3.2 -> 6.4 | O76: =N76*$E$69*(M76/365) -> 0.068558904
L77: 2028 Q1 | M77: 91 | N77: =N76-3.2 -> 3.2 | O77: =N77*$E$69*(M77/365) -> 0.033906849
B80: Term Loan - 8 | D80: 1 DHS = | E80: =E66 -> 8.5985
C82: Year | D82: Opening Balance | E82: Interest Rate | F82: Interest in INR | G82: Principal repayment | H82: Closing Balance | L82: Period | M82: Days | N82: Balance | O82: Interest
C83: 2026 | D83: =N83*E80 -> 1714.5409 | E83: 0.0575 | F83: =(SUM(O83:O86)*E80) -> 91.144877 | G83: =9.97*4*E80 -> 342.90818 | H83: =D83-G83 -> 1371.6327 | L83: 2026 Q1 | M83: 90 | N83: 199.4 | O83: =N83*$E$83*(M83/365) -> 2.8271096
C84: 2027 | D84: =H83 -> 1371.6327 | E84: 0.0575 | F84: =(SUM(O87:O90)*E80) -> 71.427656 | G84: =G83 -> 342.90818 | H84: =D84-G84 -> 1028.7245 | L84: Q2 | M84: 91 | N84: =N83-9.97 -> 189.43 | O84: =N84*$E$83*(M84/365) -> 2.7155958
C85: 2028 | D85: =H84 -> 1028.7245 | E85: 0.0575 | F85: =(SUM(O91:O94)*E80) -> 51.730767 | G85: =G84 -> 342.90818 | H85: =D85-G85 -> 685.81636 | L85: Q3 | M85: 92 | N85: =N84-9.97 -> 179.46 | O85: =N85*$E$83*(M85/365) -> 2.6009408
C86: 2029 | D86: =H85 -> 685.81636 | E86: 0.0575 | F86: =(SUM(O95:O98)*E80) -> 31.993216 | G86: =G85 -> 342.90818 | H86: =D86-G86 -> 342.90818 | L86: Q4 | M86: 92 | N86: =N85-9.97 -> 169.49 | O86: =N86*$E$83*(M86/365) -> 2.4564441
C87: 2030 | D87: =H86 -> 342.90818 | E87: 0.0575 | F87: =(SUM(O99:O102)*E80) -> 12.275995 | G87: =G86 -> 342.90818 | H87: =D87-G87 -> 0 | L87: 2027 Q1 | M87: 90 | N87: =N86-9.97 -> 159.52 | O87: =N87*E84*(M87/365) -> 2.2616877
L88: Q2 | M88: 91 | N88: =N87-9.97 -> 149.55 | O88: =N88*E85*(M88/365) -> 2.1438914
L89: Q3 | M89: 92 | N89: =N88-9.97 -> 139.58 | O89: =N89*E86*(M89/365) -> 2.022954
L90: Q4 | M90: 92 | N90: =N89-9.97 -> 129.61 | O90: =N90*E87*(M90/365) -> 1.8784573
L91: 2028 Q1 | M91: 91 | N91: =N90-9.97 -> 119.64 | O91: =N91*$E$85*(M91/366) -> 1.710427
L92: Q2 | M92: 91 | N92: =N91-9.97 -> 109.67 | O92: =N92*$E$85*(M92/366) -> 1.5678915
L93: Q3 | M93: 92 | N93: =N92-9.97 -> 99.7 | O93: =N93*$E$85*(M93/366) -> 1.4410191
L94: Q4 | M94: 92 | N94: =N93-9.97 -> 89.73 | O94: =N94*$E$85*(M94/366) -> 1.2969172
L95: 2029 Q1 | M95: 90 | N95: =N94-9.97 -> 79.76 | O95: =N95*$E$86*(M95/365) -> 1.1308438
L96: Q2 | M96: 91 | N96: =N95-9.97 -> 69.79 | O96: =N96*$E$86*(M96/365) -> 1.0004827
L97: Q3 | M97: 92 | N97: =N96-9.97 -> 59.82 | O97: =N97*$E$86*(M97/365) -> 0.86698027
L98: Q4 | M98: 92 | N98: =N97-9.97 -> 49.85 | O98: =N98*$E$86*(M98/365) -> 0.72248356
L99: 2030 Q1 | M99: 90 | N99: =N98-9.97 -> 39.88 | O99: =N99*$E$87*(M99/365) -> 0.56542192
L100: Q2 | M100: 91 | N100: =N99-9.97 -> 29.91 | O100: =N100*$E$87*(M100/365) -> 0.42877829
L101: Q3 | M101: 92 | N101: =N100-9.97 -> 19.94 | O101: =N101*$E$87*(M101/365) -> 0.28899342
L102: Q4 | M102: 92 | N102: =N101-9.97 -> 9.97 | O102: =N102*$E$87*(M102/365) -> 0.14449671
B105: Term Loan - 9 | D105: 1 DHS = | E105: =E80 -> 8.5985
C107: Total Loan= | D107: =1.46*24 -> 35.04 | E107: MDHS
C108: Payment per quarter = | D108: 1.46 | E108: MDHS
C109: Interest Rate= | D109: 0.053
C111: Year | D111: Opening Balance | E111: Q1 | F111: Q2 | G111: Q3 | H111: Q4 | I111: Total Interest | J111: Principal Repaid | M111: Q1 I | N111: Q2 I | O111: Q3 I | P111: Q4 I
C112: 2026 | D112: =D107*E105 -> 301.29144 | E112: =D112-$D$108*$E$105 -> 288.73763 | F112: =E112-$D$108*$E$105 -> 276.18382 | G112: =F112-$D$108*$E$105 -> 263.63001 | H112: =G112-$D$108*$E$105 -> 251.0762 | I112: =SUM(M112:P112) -> 14.765344 | J112: =D112-H112 -> 50.21524 | M112: =D112*$D$109*(90/365) -> 3.9374251 | N112: =E112*$D$109*(90/365) -> 3.7733657 | O112: =F112*$D$109*(90/365) -> 3.6093064 | P112: =G112*$D$109*(90/365) -> 3.445247
C113: =C112+1 -> 2027 | D113: =H112 -> 251.0762 | E113: =D113-$D$108*$E$105 -> 238.52239 | F113: =E113-$D$108*$E$105 -> 225.96858 | G113: =F113-$D$108*$E$105 -> 213.41477 | H113: =G113-$D$108*$E$105 -> 200.86096 | I113: =SUM(M113:P113) -> 12.140394 | J113: =D113-H113 -> 50.21524 | M113: =D113*$D$109*(90/365) -> 3.2811876 | N113: =E113*$D$109*(90/365) -> 3.1171282 | O113: =F113*$D$109*(90/365) -> 2.9530688 | P113: =G113*$D$109*(90/365) -> 2.7890095
C114: =C113+1 -> 2028 | D114: =H113 -> 200.86096 | E114: =D114-$D$108*$E$105 -> 188.30715 | F114: =E114-$D$108*$E$105 -> 175.75334 | G114: =F114-$D$108*$E$105 -> 163.19953 | H114: =G114-$D$108*$E$105 -> 150.64572 | I114: =SUM(M114:P114) -> 9.515444 | J114: =D114-H114 -> 50.21524 | M114: =D114*$D$109*(90/365) -> 2.6249501 | N114: =E114*$D$109*(90/365) -> 2.4608907 | O114: =F114*$D$109*(90/365) -> 2.2968313 | P114: =G114*$D$109*(90/365) -> 2.1327719
C115: =C114+1 -> 2029 | D115: =H114 -> 150.64572 | E115: =D115-$D$108*$E$105 -> 138.09191 | F115: =E115-$D$108*$E$105 -> 125.5381 | G115: =F115-$D$108*$E$105 -> 112.98429 | H115: =G115-$D$108*$E$105 -> 100.43048 | I115: =SUM(M115:P115) -> 6.890494 | J115: =D115-H115 -> 50.21524 | M115: =D115*$D$109*(90/365) -> 1.9687126 | N115: =E115*$D$109*(90/365) -> 1.8046532 | O115: =F115*$D$109*(90/365) -> 1.6405938 | P115: =G115*$D$109*(90/365) -> 1.4765344
C116: =C115+1 -> 2030 | D116: =H115 -> 100.43048 | E116: =D116-$D$108*$E$105 -> 87.87667 | F116: =E116-$D$108*$E$105 -> 75.32286 | G116: =F116-$D$108*$E$105 -> 62.76905 | H116: =G116-$D$108*$E$105 -> 50.21524 | I116: =SUM(M116:P116) -> 4.2655439 | J116: =D116-H116 -> 50.21524 | M116: =D116*$D$109*(90/365) -> 1.312475 | N116: =E116*$D$109*(90/365) -> 1.1484157 | O116: =F116*$D$109*(90/365) -> 0.98435628 | P116: =G116*$D$109*(90/365) -> 0.8202969
C117: =C116+1 -> 2031 | D117: =H116 -> 50.21524 | E117: =D117-$D$108*$E$105 -> 37.66143 | F117: =E117-$D$108*$E$105 -> 25.10762 | G117: =F117-$D$108*$E$105 -> 12.55381 | H117: =G117-$D$108*$E$105 -> 0 | I117: =SUM(M117:P117) -> 1.6405938 | J117: =D117-H117 -> 50.21524 | M117: =D117*$D$109*(90/365) -> 0.65623752 | N117: =E117*$D$109*(90/365) -> 0.49217814 | O117: =F117*$D$109*(90/365) -> 0.32811876 | P117: =G117*$D$109*(90/365) -> 0.16405938
B119: Total
C120: Year | D120: Opening Balance | E120: Interest Paid | F120: Principal Paid | G120: Closing Balance
C121: 2026 | D121: =D69+D83+D112+D64 -> 2276.6291 | E121: =F69+F83+I112 -> 114.66948 | F121: =G69+G83+J112+D64 -> 516.34422 | G121: =H112+H83+H69 -> 1760.2849
C122: =C121+1 -> 2027 | D122: =D70+D84+D113 -> 1760.2849 | E122: =F70+F84+I113 -> 87.649723 | F122: =G70+G84+J113 -> 503.18342 | G122: =H113+H84+H70 -> 1257.1015
C123: =C122+1 -> 2028 | D123: =D71+D85+D114 -> 1257.1015 | E123: =F71+F85+I114 -> 61.537759 | F123: =G71+G85+J114 -> 420.63942 | G123: =H114+H85+H71 -> 836.46208
C124: =C123+1 -> 2029 | D124: =D72+D86+D115 -> 836.46208 | E124: =F72+F86+I115 -> 38.88371 | F124: =G72+G86+J115 -> 393.12342 | G124: =H115+H86+H72 -> 443.33866
C125: =C124+1 -> 2030 | D125: =D73+D87+D116 -> 443.33866 | E125: =F73+F87+I116 -> 16.541539 | F125: =G73+G87+J116 -> 393.12342 | G125: =H116+H87+H73 -> 50.21524
C126: =C125+1 -> 2031 | D126: =D74+D88+D117 -> 50.21524 | E126: =F74+F88+I117 -> 1.6405938 | F126: =G74+G88+J117 -> 50.21524 | G126: =H117+H88+H74 -> 0
...

Sheet Spare
A2: VARUN BEVERAGES
A3: Assumptions
B5: First year of forecast | D5: 2026 | K5: =$D$5 -> 2026 | L5: =K5+1 -> 2027 | M5: =L5+1 -> 2028 | N5: =M5+1 -> 2029 | O5: =N5+1 -> 2030
C6: Inflation Rate for Capex | D6: 0.05
B8: Scenarios
B10: India Volume Growth % | D10: 1 | K10: =CHOOSE($D$10,K12,K13,K14) -> 0.11 | L10: =CHOOSE($D$10,L12,L13,L14) -> 0.1 | M10: =CHOOSE($D$10,M12,M13,M14) -> 0.09 | N10: =CHOOSE($D$10,N12,N13,N14) -> 0.08 | O10: =CHOOSE($D$10,O12,O13,O14) -> 0.07
B12: Base Case | K12: 0.11 | L12: 0.1 | M12: 0.09 | N12: 0.08 | O12: 0.07
B13: Best Case | K13: 0.14 | L13: 0.13 | M13: 0.13 | N13: 0.13 | O13: 0.13
B14: Worst Case | K14: 0.08 | L14: 0.08 | M14: 0.07 | N14: 0.06 | O14: 0.05
B16: International Volume Growth % | D16: 1 | K16: =CHOOSE($D$16,K18,K19,K20) -> 0.3 | L16: =CHOOSE($D$16,L18,L19,L20) -> 0.15 | M16: =CHOOSE($D$16,M18,M19,M20) -> 0.14 | N16: =CHOOSE($D$16,N18,N19,N20) -> 0.13 | O16: =CHOOSE($D$16,O18,O19,O20) -> 0.12
B18: Base Case | K18: 0.3 | L18: 0.15 | M18: 0.14 | N18: 0.13 | O18: 0.12
B19: Best Case | K19: 0.34 | L19: 0.17 | M19: 0.16 | N19: 0.15 | O19: 0.14
B20: Worst Case | K20: 0.24 | L20: 0.1 | M20: 0.1 | N20: 0.1 | O20: 0.1
B22: India realization per case Growth % | D22: 1 | K22: =CHOOSE($D$22,K24,K25,K26) -> 0.005 | L22: =CHOOSE($D$22,L24,L25,L26) -> 0.015 | M22: =CHOOSE($D$22,M24,M25,M26) -> 0.02 | N22: =CHOOSE($D$22,N24,N25,N26) -> 0.025 | O22: =CHOOSE($D$22,O24,O25,O26) -> 0.025
B24: Base Case | K24: 0.005 | L24: 0.015 | M24: 0.02 | N24: 0.025 | O24: 0.025
B25: Best Case | K25: 0.02 | L25: 0.03 | M25: 0.04 | N25: 0.04 | O25: 0.04
B26: Worst Case | K26: -0.015 | L26: -0.005 | M26: 0.005 | N26: 0.01 | O26: 0.01
B28: International realization per case Growth % | D28: 1 | K28: =CHOOSE($D$28,K30,K31,K32) -> 0.06 | L28: =CHOOSE($D$28,L30,L31,L32) -> 0.025 | M28: =CHOOSE($D$28,M30,M31,M32) -> 0.025 | N28: =CHOOSE($D$28,N30,N31,N32) -> 0.025 | O28: =CHOOSE($D$28,O30,O31,O32) -> 0.025
B30: Base Case | K30: 0.06 | L30: 0.025 | M30: 0.025 | N30: 0.025 | O30: 0.025
B31: Best Case | K31: 0.09 | L31: 0.045 | M31: 0.04 | N31: 0.04 | O31: 0.04
B32: Worst Case | K32: 0.01 | L32: 0 | M32: 0.01 | N32: 0.015 | O32: 0.015
B35: India Revenue
C36: Volume growth % | D36: (%) | K36: =K10 -> 0.11 | L36: =L10 -> 0.1 | M36: =M10 -> 0.09 | N36: =N10 -> 0.08 | O36: =O10 -> 0.07
C37: Realization per case growth % | D37: (%) | K37: =K22 -> 0.005 | L37: =L22 -> 0.015 | M37: =M22 -> 0.02 | N37: =N22 -> 0.025 | O37: =O22 -> 0.025
B39: International Revenue
C40: Volume growth rate | D40: (%) | K40: =K16 -> 0.3 | L40: =L16 -> 0.15 | M40: =M16 -> 0.14 | N40: =N16 -> 0.13 | O40: =O16 -> 0.12
C41: Realization per case growth % | D41: (%) | K41: =K28 -> 0.06 | L41: =L28 -> 0.025 | M41: =M28 -> 0.025 | N41: =N28 -> 0.025 | O41: =O28 -> 0.025
C42: Excise Duty % | D42: (%) | K42: =$J$246 -> 0.077229313 | L42: =$J$246 -> 0.077229313 | M42: =$J$246 -> 0.077229313 | N42: =$J$246 -> 0.077229313 | O42: =$J$246 -> 0.077229313
B45: Cost Schedule
C46: Margin for Cost of materials consumed | D46: (%) | K46: =$J$258 -> 0.44400923 | L46: =$J$258 -> 0.44400923 | M46: =$J$258 -> 0.44400923 | N46: =$J$258 -> 0.44400923 | O46: =$J$258 -> 0.44400923
C47: Other Expenses | D47: (%) | K47: =$J$263 -> 0.22556761 | L47: =$J$263 -> 0.22556761 | M47: =$J$263 -> 0.22556761 | N47: =$J$263 -> 0.22556761 | O47: =$J$263 -> 0.22556761
B50: Capex-Split Trend
C52: Land | E52: 0.02042
C53: Building + Plant & Equipment | E53: 0.81134
C54: Distribution & Others | E54: 0.16824
B56: Fixed Asset Schedule
C57: India Expansion Capex | K57: 5000 | L57: =K57*(1+$D$6) -> 5250 | M57: =L57*(1+$D$6) -> 5512.5 | N57: =M57*(1+$D$6) -> 5788.125 | O57: =N57*(1+$D$6) -> 6077.5312
C58: Total Maintenance Capex | J58: 10634.17 | K58: =J58*(1+$D$6) -> 11165.879 | L58: =K406 -> 13102.579 | M58: =L406 -> 14023.968 | N58: =M406 -> 15004.45 | O58: =N406 -> 16083.35
C59: Expansion Towards South Africa and CSD line in Kenya (CWIP) | K59: 4900
C60: CWIP Transfer to PPE
C61: Inorganic implied PPE added due to acquisition of Twizza South Africa | K61: 3144
C62: Total Capex | K62: =SUM(K57:K61) -> 24209.878 | L62: =SUM(L57:L61) -> 18352.579 | M62: =SUM(M57:M61) -> 19536.468 | N62: =SUM(N57:N61) -> 20792.575 | O62: =SUM(O57:O61) -> 22160.881
C64: CWIP routing share to transfer to Building, Plant & Equipment (50%) | J64: 0.5
B67: Debt Schedule
C68: Minimum Cash Balance | J68: 1889.34 | K68: =J68*(1+K283) -> 2270.6546 | L68: =K68*(1+L283) -> 2588.4621 | M68: =L68*(1+M283) -> 2935.0525 | N68: =M68*(1+N283) -> 3309.5172 | O68: =N68*(1+O283) -> 3699.6876
C69: ST Interest rate | K69: 0.1025 | L69: =K69 -> 0.1025 | M69: =L69 -> 0.1025 | N69: =M69 -> 0.1025 | O69: =N69 -> 0.1025
C70: Interest rate on Cash and cash equivalents | K70: 0.06 | L70: =K70 -> 0.06 | M70: =L70 -> 0.06 | N70: =M70 -> 0.06 | O70: =N70 -> 0.06
B72: TWIZZA Integaration
C73: Goodwill | K73: 4689.19
C74: Other Intangible Assets | K74: 3481.33
C75: PPE Implied | K75: 3144
C76: Total | K76: =SUM(K73:K75) -> 11314.52
A80: Income Statement
A82: Income Statement (in millions of INR) | F82: =G82-1 -> 2021 | G82: =H82-1 -> 2022 | H82: =I82-1 -> 2023 | I82: =J82-1 -> 2024 | J82: =K82-1 -> 2025 | K82: =K5 -> 2026 | L82: =L5 -> 2027 | M82: =M5 -> 2028 | N82: =N5 -> 2029 | O82: =O5 -> 2030
B84: 1. Income
C85: Revenue from operations | F85: 89582.91 | G85: 133905.58 | H85: 163210.63 | I85: 204813.28 | J85: 222255.84 | K85: =K87-K86 -> 268206.5 | L85: =L87-L86 -> 306039.71 | M85: =M87-M86 -> 347327.31 | N85: =N87-N86 -> 391961.03 | O85: =O87-O86 -> 438535.04
C86: Excise Duty | F86: -1350.61 | G86: -2174.16 | H86: -2784.82 | I86: -4736.78 | J86: -5402.05 | K86: =-K244 -> -7586.3524 | L86: =-L244 -> -8942.4129 | M86: =-M244 -> -10449.21 | N86: =-N244 -> -12102.797 | O86: =-O244 -> -13894.011
B87: Net Revenues | F87: =F85+F86 -> 88232.3 | G87: =G85+G86 -> 131731.42 | H87: =H85+H86 -> 160425.81 | I87: =I85+I86 -> 200076.5 | J87: =J85+J86 -> 216853.79 | K87: =K242 -> 260620.14 | L87: =L242 -> 297097.3 | M87: =M242 -> 336878.1 | N87: =N242 -> 379858.23 | O87: =O242 -> 424641.03
C88: Other Income | F88: 679.25 | G88: 388.49 | H88: 793.59 | I88: 1212.68 | J88: 3523.48 | K88: =K424 -> 756.83035 | L88: =L424 -> 918.221 | M88: =M424 -> 2300.5224 | N88: =N424 -> 4041.0744 | O88: =O424 -> 6174.8103
B90: 2. Expenses
C91: Cost of materials consumed | F91: 39689.13 | G91: 64170.92 | H91: 70264.61 | I91: 82937.43 | J91: 93370.62 | K91: =K87*K46 -> 115717.75 | L91: =L87*L46 -> 131913.94 | M91: =M87*M46 -> 149576.98 | N91: =N87*N46 -> 168660.56 | O91: =O87*O46 -> 188544.54
C92: Purchase of stock-in-trade | F92: 1654.69 | G92: 1885.71 | H92: 4626.96 | I92: 6859.21 | J92: 3694.53 | K92: =K274 -> 5902.0163 | L92: =L274 -> 6728.0798 | M92: =M274 -> 7628.9576 | N92: =N274 -> 8602.2878 | O92: =O274 -> 9616.4412
C93: Changes in inventories of FG, WIP and stock-in-trade | F93: -997.22 | G93: -3445.07 | H93: -842.69 | I93: -749.4 | J93: 89.14 | K93: 0 | L93: 0 | M93: 0 | N93: 0 | O93: 0
C94: Employee benefits expense | F94: 10076.99 | G94: 12166.42 | H94: 14465.87 | I94: 18850.26 | J94: 22007.43 | K94: =K269 -> 25667.936 | L94: =L269 -> 29260.496 | M94: =M269 -> 33178.424 | N94: =N269 -> 37411.448 | O94: =O269 -> 41822.013
C95: Finance costs | F95: 1847 | G95: 1861.22 | H95: 2680.99 | I95: 4503.86 | J95: 1695.79 | K95: =K451 -> 1538.5461 | L95: =L451 -> 760.40856 | M95: =M451 -> 654.47932 | N95: =N451 -> 571.32916 | O95: =O451 -> 530.73154
C96: Depreciation, amortization expense | F96: 5312.62 | G96: 6171.89 | H96: 6809.06 | I96: 9473.86 | J96: 12164.63 | K96: =K495 -> 14704.663 | L96: =L495 -> 15918.178 | M96: =M495 -> 16898.66 | N96: =N495 -> 17977.56 | O96: =O495 -> 19148.93
C97: Other expenses | F97: 21262.26 | G97: 29072.39 | H97: 35816.21 | I97: 45068.29 | J97: 47198.38 | K97: =K264 -> 58787.462 | L97: =L264 -> 67015.527 | M97: =M264 -> 75988.786 | N97: =N264 -> 85683.712 | O97: =O264 -> 95785.261
B98: Total Expenses | F98: =SUM(F91:F97) -> 78845.47 | G98: =SUM(G91:G97) -> 111883.48 | H98: =SUM(H91:H97) -> 133821.01 | I98: =SUM(I91:I97) -> 166943.51 | J98: =SUM(J91:J97) -> 180220.52 | K98: =SUM(K91:K97) -> 222318.37 | L98: =SUM(L91:L97) -> 251596.63 | M98: =SUM(M91:M97) -> 283926.29 | ... O98: =SUM(O91:O97) -> 355447.91
B100: EBITDA | F100: =F87-F98+F96+F95 -> 16546.45 | G100: =G87-G98+G96+G95 -> 27881.05 | H100: =H87-H98+H96+H95 -> 36094.85 | I100: =I87-I98+I96+I95 -> 47110.71 | J100: =J87-J98+J96+J95 -> 50493.69 | K100: =K87-K98+K96+K95 -> 54544.979 | L100: =L87-L98+L96+L95 -> 62179.254 | M100: =M87-M98+M96+M95 -> 70504.945 | ... O100: =O87-O98+O96+O95 -> 88872.778
B102: 3. Profit before share of loss of associate and joint venture | F102: =F87+F88-F98 -> 10066.08 | G102: =G87+G88-G98 -> 20236.43 | H102: =H87+H88-H98 -> 27398.39 | I102: =I87+I88-I98 -> 34345.67 | J102: =J87+J88-J98 -> 40156.75 | K102: =K87+K88-K98 -> 39058.601 | L102: =L87+L88-L98 -> 46418.889 | M102: =M87+M88-M98 -> 55252.327 | ... O102: =O87+O88-O98 -> 75367.927
B103: 4. Share of loss of associate and joint venture | F103: 0 | G103: -0.06 | H103: -4.79 | I103: -14.78 | J103: -60.27 | K103: 0 | L103: 0 | M103: 0 | N103: 0 | O103: 0
B104: 5. Profit before tax | F104: =F102+F103 -> 10066.08 | G104: =G102+G103 -> 20236.37 | H104: =H102+H103 -> 27393.6 | I104: =I102+I103 -> 34330.89 | J104: =J102+J103 -> 40096.48 | K104: =K102+K103 -> 39058.601 | L104: =L102+L103 -> 46418.889 | M104: =M102+M103 -> 55252.327 | ... O104: =O102+O103 -> 75367.927
B105: 6. Tax expense | F105: -2605.56 | G105: -4735.23 | H105: -6375.47 | I105: -7988.04 | J105: -9476.06 | K105: =-K519 -> -9136.3943 | L105: =-L519 -> -10858.076 | M105: =-M519 -> -12924.351 | N105: =-N519 -> -15202.702 | O105: =-O519 -> -17629.692
B106: 7. Net Income | F106: =F104+F105 -> 7460.52 | G106: =G104+G105 -> 15501.14 | H106: =H104+H105 -> 21018.13 | I106: =I104+I105 -> 26342.85 | J106: =J104+J105 -> 30620.42 | K106: =K104+K105 -> 29922.206 | L106: =L104+L105 -> 35560.812 | M106: =M104+M105 -> 42327.977 | ... O106: =O104+O105 -> 57738.235
B107: 8. Non-controlling interest | F107: -520 | G107: -553.81 | H107: -458.91 | I107: -396.52 | J107: -255.53
B108: 9. Net income attributable to equity shareholders | F108: =F106+F107 -> 6940.52 | G108: =G106+G107 -> 14947.33 | H108: =H106+H107 -> 20559.22 | I108: =I106+I107 -> 25946.33 | J108: =J106+J107 -> 30364.89 | K108: =K106+K107 -> 29922.206 | L108: =L106+L107 -> 35560.812 | M108: =M106+M107 -> 42327.977 | ... O108: =O106+O107 -> 57738.235
B111: Weighted-average share count (basic) | D111: (000s) | F111: 3246825 | G111: 3246825 | H111: 3246875 | I111: 3278350 | J111: 3381750 | K111: =K540 -> 3381750 | L111: =L540 -> 3381750 | M111: =M540 -> 3381750 | N111: =N540 -> 3381750 | O111: =O540 -> 3381750
B112: Weighted-average share count (diluted) | D112: (000s) | F112: 3248500 | G112: 3248750 | H112: 3248928 | I112: 3280500 | J112: 3383500 | K112: =K543 -> 3383500 | L112: =L543 -> 3383500 | M112: =M543 -> 3383500 | N112: =N543 -> 3383500 | O112: =O543 -> 3383500
B113: EPS
B114: Basic | D114: INR | F114: =(F$108/F111)*1000 -> 2.1376329 | G114: =(G$108/G111)*1000 -> 4.6036759 | H114: =(H$108/H111)*1000 -> 6.3320023 | I114: =(I$108/I111)*1000 -> 7.9144478 | J114: =(J$108/J111)*1000 -> 8.9790464 | K114: =(K$108/K111)*1000 -> 8.8481426 | L114: =(L$108/L111)*1000 -> 10.515506 | M114: =(M$108/M111)*1000 -> 12.51659 | ... O114: =(O$108/O111)*1000 -> 17.073478
B115: Diluted | D115: INR | F115: =(F$108/F112)*1000 -> 2.1365307 | G115: =(G$108/G112)*1000 -> 4.6009481 | H115: =(H$108/H112)*1000 -> 6.3280011 | I115: =(I$108/I112)*1000 -> 7.9092608 | J115: =(J$108/J112)*1000 -> 8.9744022 | K115: =(K$108/K112)*1000 -> 8.8435662 | L115: =(L$108/L112)*1000 -> 10.510067 | M115: =(M$108/M112)*1000 -> 12.510116 | ... O115: =(O$108/O112)*1000 -> 17.064648
A119: Cash Flow Statement
A121: Cash Flow Statement (in millions of INR) | F121: =G121-1 -> 2021 | G121: =H121-1 -> 2022 | H121: =I121-1 -> 2023 | I121: =J121-1 -> 2024 | J121: =K121-1 -> 2025 | K121: =K$82 -> 2026 | L121: =L$82 -> 2027 | M121: =M$82 -> 2028 | N121: =N$82 -> 2029 | O121: =O$82 -> 2030
B122: A. Cash Flows from Operating activities
C123: Profit before tax and share of loss in associates and joint ventures | F123: 10066.08 | G123: 20236.43 | H123: 27398.39 | I123: 34345.67 | J123: 40156.75 | K123: =K102 -> 39058.601 | L123: =L102 -> 46418.889 | M123: =M102 -> 55252.327 | N123: =N102 -> 64992.408 | O123: =O102 -> 75367.927
B125: Adjustment to reconcile profit before tax to net cash flows:
C126: Depreciation and impairment on property, plant and equipment | F126: 5037.54 | G126: 5830.99 | H126: 6409.04 | I126: 8386.95 | J126: 10634.17 | K126: =K406 -> 13102.579 | L126: =L406 -> 14023.968 | M126: =M406 -> 15004.45 | N126: =N406 -> 16083.35 | O126: =O406 -> 17254.719
C127: Amortisation of intangible assets and right of use assets | F127: 275.08 | G127: 340.9 | H127: 400.02 | I127: 1086.91 | J127: 1530.46 | K127: =K494 -> 1602.0835 | L127: =L494 -> 1894.2103 | M127: =M494 -> 1894.2103 | N127: =N494 -> 1894.2103 | O127: =O494 -> 1894.2103
C128: Interest expense at amortised cost | F128: 1850.37 | G128: 1854.49 | H128: 2680.99 | I128: 4503.86 | J128: 1695.79 | K128: =K451 -> 1538.5461 | L128: =L451 -> 760.40856 | M128: =M451 -> 654.47932 | N128: =N451 -> 571.32916 | O128: =O451 -> 530.73154
C129: Interest income at amortised cost | F129: -145.16 | G129: -228.29 | H129: -238 | I129: -419 | J129: -317.65 | K129: =-K424 -> -756.83035 | L129: =-L424 -> -918.221 | M129: =-M424 -> -2300.5224 | N129: =-N424 -> -4041.0744 | O129: =-O424 -> -6174.8103
C130: Total Provisions & Non-Cash Write-offs | F130: 0.54 | G130: 90.02 | H130: -249.65 | I130: -532.57 | J130: 69.62 | K130: 0 | L130: 0 | M130: 0 | N130: 0 | O130: 0
C131: Gains / Losses on Asset Disposals & Investments | F131: 258.01 | G131: 619.59 | H131: 839.32 | I131: 739.41 | J131: -838.84 | K131: 0 | L131: 0 | M131: 0 | N131: 0 | O131: 0
C132: Other Non-Operating Accounting Adjustments | F132: -1098.5 | G132: -1258.62 | H132: 81.87 | I132: -330.72 | J132: -3245.11 | K132: =K502 -> 976.45801 | L132: =L502 -> 813.83097 | M132: =M502 -> 887.53739 | N132: =N502 -> 958.91696 | O132: =O502 -> 999.13561
C134: Operating profit before working capital changes | F134: =F123+(SUM(F126:F132)) -> 16243.96 | G134: =G123+(SUM(G126:G132)) -> 27485.51 | H134: =H123+(SUM(H126:H132)) -> 37321.98 | I134: =I123+(SUM(I126:I132)) -> 47780.51 | J134: =J123+(SUM(J126:J132)) -> 49685.19 | K134: =K123+(SUM(K126:K132)) -> 55521.437 | L134: =L123+(SUM(L126:L132)) -> 62993.085 | M134: =M123+(SUM(M126:M132)) -> 71392.482 | ... O134: =O123+(SUM(O126:O132)) -> 89871.914
B136: Working capital adjustments
C137: Inventories | F137: -5192.83 | G137: -5568.33 | H137: -1601.73 | I137: -4787.7 | J137: 147.84 | K137: =K309 -> -7064.7502 | L137: =L309 -> -5120.2135 | M137: =M309 -> -5583.937 | N137: =N309 -> -6033.0213 | O137: =O309 -> -6286.0567
C138: Trade Receivables | F138: 146.56 | G138: -1233.8 | H138: -730.18 | I138: -1332.15 | J138: -2851.03 | K138: =K308 -> -2520.8474 | L138: =L308 -> -2101.0056 | M138: =M308 -> -2291.2878 | N138: =N308 -> -2475.5631 | O138: =O308 -> -2579.3925
C139: Inc. in Financial & Other Assets | F139: -921.85 | G139: -3257.13 | H139: -4572.18 | I139: -5224.3 | J139: 2230.71 | K139: =K310 -> -3411.0155 | L139: =L310 -> -2842.918 | M139: =M310 -> -3100.3932 | N139: =N310 -> -3349.7402 | O139: =O310 -> -3490.2341
C140: Inc. in Financial & Other Liabilities & Provisions | F140: 3280.66 | G140: 4207.33 | H140: 169.28 | I140: 4650.27 | J140: -5238.06 | K140: =K306 -> 4738.3684 | L140: =L306 -> 3320.1724 | M140: =M306 -> 3620.8712 | N140: =N306 -> 3912.0773 | O140: =O306 -> 4076.1566
C141: Total Cash from Operations | F141: =F134+(SUM(F137:F140)) -> 13556.5 | G141: =G134+(SUM(G137:G140)) -> 21633.58 | H141: =H134+(SUM(H137:H140)) -> 30587.17 | I141: =I134+(SUM(I137:I140)) -> 41086.63 | J141: =J134+(SUM(J137:J140)) -> 43974.65 | K141: =K134+(SUM(K137:K140)) -> 47263.193 | L141: =L134+(SUM(L137:L140)) -> 56249.121 | M141: =M134+(SUM(M137:M140)) -> 64037.735 | ... O141: =O134+(SUM(O137:O140)) -> 81592.387
...

Sheet Sheet1
